[
  {
    "id": "common-1",
    "title": "汎用テーマ（A) ※個人応援歌のない選手",
    "category": "anthem",
    "lyrics": [
      "{夢|ゆめ}を{見|み}た",
      "この{世界|せかい}で",
      "{勝利|しょうり}の{雄叫|おたけ}び{上|あ}げろ",
      "{若獅子|わかじし}の{力|ちから}を",
      "{見|み}せてくれ"
    ],
    "isCommon": true,
    "url": "https://www.youtube.com/watch?v=hmElk2vl6_Y"
  },
  {
    "id": "common-2",
    "title": "汎用テーマ (B) ※個人応援歌のない選手",
    "category": "anthem",
    "lyrics": [
      "{流|なが}した{汗|あせ}はすべて",
      "{努力|どりょく}の{結晶|けっしょう}だ",
      "がむしゃらに{掴|つか}めチャンス",
      "いけ! {{name}}!"
    ],
    "isCommon": true,
    "url": "https://www.youtube.com/watch?v=dblqxLilk6A",
    "namePlaceholder": "{{name}}"
  },
  {
    "id": "common-3",
    "title": "外国人選手汎用テーマ ※個人応援歌のない外国人選手(野手)",
    "category": "anthem",
    "lyrics": [
      "{感情|かんじょう}を{昂|たかぶ}らせ",
      "{見|み}せろフルスイング",
      "{決|き}め{球|だま}{砕|くだ}いて",
      "{虹|にじ}を{描|えが}く"
    ],
    "isCommon": true,
    "url": "https://www.youtube.com/watch?v=07qIExX9Bjg"
  },
  {
    "id": "common-11",
    "title": "フラッグ トゥ ビクトリー",
    "category": "anthem",
    "lyrics": [
      "{打|う}てー! {{name}}{打|う}てー! {{name}}{打|う}てー! {{name}}{打|う}てー! {{name}}!",
      "ララララー ラララーラーララーラーラー",
      "ララララーララーオーオーオオオー",
      "オーオオーオーオーオーオ オー"
    ],
    "isCommon": true,
    "namePlaceholder": "{{name}}",
    "url": "https://www.youtube.com/watch?v=nV4_9FUlGYE"
  },
  {
    "id": "common-12",
    "title": "かっ飛ばせ若獅子",
    "category": "anthem",
    "lyrics": [
      "{若獅子|わかじし}{打線|だせん}だソーリャセ",
      "{右|みぎ}に{左|ひだり}に{乱|みだ}れ{打|う}ち",
      "カッセ! カッセ! カッセカッセカッセ!"
    ],
    "isCommon": true,
    "url": "https://www.youtube.com/watch?v=w108s81hLFc"
  },
  {
    "id": "common-15",
    "title": "サンバソーリャセ",
    "category": "anthem",
    "lyrics": [
      "ソーリャセ ソーリャセ",
      "ソーリャセソーリャセ",
      "ソーリャセソリャセ{{name}}",
      "ソリャセ{{name}} ソリャセ{{name}} ソリャセ{{name}}"
    ],
    "isCommon": true,
    "namePlaceholder": "{{name}}",
    "url": "https://www.youtube.com/watch?v=OlT42x10sMQ"
  },
  {
    "id": "common-16",
    "title": "吠えろライオンズ",
    "category": "anthem",
    "lyrics": [
      "{吠|ほ}えろライオン かっ{飛|と}ばせライオン",
      "{吠|ほ}えろライオン {西武|せいぶ}ライオンズ",
      "{僕|ぼく}らは{待|ま}っている {輝|かがや}きの{瞬間|しゅんかん}",
      "{熱|あつ}く{燃|も}える{手|て}で{勝利|しょうり}をつかめ",
      "{打|う}てよ {走|はし}れよ {戦|たたか}いはこれから (Go! Go!)",
      "{吠|ほ}えろライオン かっ{飛|と}ばせライオン",
      "{吠|ほ}えろライオン {西武|せいぶ}ライオンズ",
      "{僕|ぼく}らは{知|し}っている {君|きみ}たちの{勇気|ゆうき}を",
      "なびくたて{髪|がみ}は {王者|おうじゃ}のしるし",
      "{投|な}げろ{守|まも}れよ {戦|たたか}いはこれから (Go! Go!)",
      "{吠|ほ}えろライオン {西武|せいぶ}ライオンズ",
      "{燃|も}えろライオン {突|つ}っ{走|ぱし}れライオン",
      "{燃|も}えろライオン {西武|せいぶ}ライオンズ",
      "（LIONS ライオンズ）",
      "（FIGHT ファイト） （LIONS ライオンズ）",
      "(Let's Go Let's Go Wooh Yeah!)",
      "{終|お}わりのない{旅|たび}を みんなで{突|つ}き{進|すす}め"
    ],
    "isCommon": true,
    "url": "https://www.youtube.com/watch?v=gaFtb-_Vp7Y"
  },
  {
    "id": "common-17",
    "title": "若き獅子たち",
    "category": "anthem",
    "lyrics": [
      "{緑|みどり}の{森|もり}に いま{湧|わ}きあがる",
      "{熱|あつ}い{祈|いの}りの{大歓声|だいかんせい}が",
      "きたえぬかれた {若|わか}き{獅子|しし}たち",
      "{気高|けだか}く{進|すす}め {勝利|しょうり}はそこに",
      "ウィー・アー・ザ・ライオンズ",
      "オー・オー・オー・ライオンズ",
      "",
      "{苦|くる}しい{時|とき}も {手|て}をさしのべて",
      "{強|つよ}きものこそ やさしくなれる",
      "{天|てん}にはばたく {若|わか}き{獅子|しし}たち",
      "{見|み}はてぬ{夢|ゆめ}に {想|おも}いよとどけ",
      "ウィー・アー・ザ・ライオンズ",
      "オー・オー・オー・ライオンズ",
      "",
      "{闘|たたか}うものは ただひたすらに",
      "{燃|も}えよ この{時|とき} {力|ちから}のかぎり",
      "{今日|きょう}もゆるがぬ {若|わか}き{獅子|しし}たち",
      "{肩|かた}くみ{謳|うた}う {勝利|しょうり}はここに",
      "ウィー・アー・ザ・ライオンズ",
      "オー・オー・オー・ライオンズ",
      "ウィー・アー・ザ・ライオンズ",
      "オー・オー・オー・ライオンズ"
    ],
    "isCommon": true,
    "url": "https://www.youtube.com/watch?v=Bimp3mm16Gg"
  },
  {
    "id": "common-18",
    "title": "新Vのシナリオ",
    "category": "anthem",
    "lyrics": [
      "Oh レオがゆくよ {常勝|じょうしょう}{軍団|ぐんだん}",
      "{埼玉|さいたま}{西武|せいぶ}{皆|みな}の{希望|きぼう}と{夢|ゆめ}のチーム",
      "Wow Wow ライオンズ",
      "{永久|とわ}の{道|みち}を{今|いま}{光|ひかり}を{飛|と}び{越|こ}えて",
      "Oh レオがゆくよ"
    ],
    "isCommon": true,
    "url": "https://www.youtube.com/watch?v=SBRZz3MbxEQ"
  },
  {
    "id": "common-19",
    "title": "【球団歌】 地平を駈ける獅子を見た",
    "category": "anthem",
    "lyrics": [
      "アアア ライオンズライオンズライオンズ",
      "ミラクル{元年|がんねん}{奇跡|きせき}を{呼|よ}んで",
      "{獅子|しし}よ{吠|ほ}えろよ{限|かぎ}りなくライオンズ",
      "WowWowWow ライオンズ WowWowWow ライオンズ ライオンズ"
    ],
    "isCommon": true,
    "url": "https://www.youtube.com/watch?v=EZXntHLSDVc"
  },
  {
    "id": "common-20",
    "title": "大宮限定",
    "category": "anthem",
    "lyrics": [
      "{大宮|おおみや} オーオー {{name}}",
      "オオオオー{蒼|あお}く{染|そ}められた",
      "{輝|かがや}け{大宮|おおみや}で"
    ],
    "isCommon": true,
    "namePlaceholder": "{{name}}",
    "url": "https://www.youtube.com/watch?v=YAeqmHliH7Y"
  },
  {
    "id": "common-21",
    "title": "東北限定",
    "category": "anthem",
    "lyrics": [
      "{行|い}くぞ{東北|とうほく}で",
      "{勝利|しょうり}を{掴|つか}みとれ",
      "オオオ オーオオオーオオ オオオ オーオオオーオーオー",
      "{埼玉|さいたま} {西武|せいぶ} レッツゴー レッツゴー {{name}}"
    ],
    "isCommon": true,
    "namePlaceholder": "{{name}}",
    "url": "https://www.youtube.com/watch?v=ix0hzzcop_U"
  }
]
